{"rating": 9.0, "genres": ["Adventure", "Western"], "rated": "APPROVED", "filming_locations": "Almer\u00eda, Andaluc\u00eda, Spain", "language": ["Italian"], "plot": "Blondie (The Good) is a professional gunslinger who is out trying to earn a few dollars. Angel Eyes (The Bad) is a hit man who always commits to a task and sees it through, as long as he is paid to do so. And Tuco (The Ugly) is a wanted outlaw trying to take care of his own hide. Tuco and Blondie share a partnership together making money off Tuco's bounty, but when Blondie unties the partnership, Tuco tries to hunt down Blondie. When Blondie and Tuco comes across a horse carriage loaded with dead bodies, they soon learn from the only survivor (Bill Carson) that he and a few other men have buried a stash of gold in a cemetery. Unfortunately Carson dies and Tuco only finds out the name of the cemetery, while Blondie finds out the name on the grave. Now the two must keep each other alive in order to find the gold. Angel Eyes (who had been looking for Bill Carson) discovers that Tuco and Blondie meet with Carson and knows they know the location of the gold...", "runtime": ["161 min", "France: 186 min (dubbed version)", "Spain: 182 min", "179 min (2003 extended English version)", "Finland: 142 min (1984) (cut version)"], "poster": "http://img3.douban.com/lpic/s4008151.jpg", "imdb_url": "http://www.imdb.com/title/tt0060196/", "title": "Il buono, il brutto, il cattivo.", "writers": ["Luciano Vincenzoni", "Sergio Leone"], "imdb_id": "tt0060196", "directors": ["Sergio Leone"], "rating_count": 274781, "actors": ["Eli Wallach", "Clint Eastwood", "Lee Van Cleef", "Aldo Giuffr\u00e8", "Luigi Pistilli", "Rada Rassimov", "Enzo Petito", "Claudio Scarchilli", "John Bartha", "Livio Lorenzon", "Antonio Casale", "Sandro Scarchilli", "Benito Stefanelli", "Angelo Novi", "Antonio Casas"], "plot_simple": "A bounty hunting scam joins two men in an uneasy alliance against a third in a race to find a fortune in gold buried in a remote cemetery.", "year": 1966, "country": ["Italy", "Spain", "West Germany"], "type": "M", "release_date": 19671229, "also_known_as": ["The Good, the Bad and the Ugly"]}