{"rating": 8.4, "genres": ["Drama"], "rated": "UNRATED", "filming_locations": "Brooklyn, New York City, New York, USA", "language": ["English"], "plot": "Drugs. They consume mind, body and soul. Once you're hooked, you're hooked. Four lives. Four addicts. Four failures. Despite their aspirations of greatness, they succumb to their addictions. Watching the addicts spiral out of control, we bear witness to the dirtiest, ugliest portions of the underworld addicts reside in. It is shocking and eye-opening but demands to be seen by both addicts and non-addicts alike.", "runtime": ["102 min"], "poster": "http://img3.douban.com/lpic/s2155554.jpg", "imdb_url": "http://www.imdb.com/title/tt0180093/", "title": "Requiem for a Dream", "writers": ["Hubert Selby Jr.", "Hubert Selby Jr.", "and 1 more credit"], "imdb_id": "tt0180093", "directors": ["Darren Aronofsky"], "rating_count": 321308, "actors": ["Ellen Burstyn", "Jared Leto", "Jennifer Connelly", "Marlon Wayans", "Christopher McDonald", "Louise Lasser", "Marcia Jean Kurtz", "Janet Sarno", "Suzanne Shepherd", "Joanne Gordon", "Charlotte Aronofsky", "Mark Margolis", "Michael Kaycheck", "Jack O'Connell", "Chas Mastin"], "plot_simple": "The drug-induced utopias of four Coney Island individuals are shattered when their addictions become stronger.", "year": 2000, "country": ["USA"], "type": "M", "release_date": 20001027, "also_known_as": ["R\u00e9quiem por un sue\u00f1o"]}